gee_whiz_2/__init__.py
gee_whiz_2/_version.py
gee_whiz_2/addon/__init__.py
gee_whiz_2/cli/__init__.py
gee_whiz_2/cli/config.py
gee_whiz_2/cli/main.py
gee_whiz_2/cli/profile.py
gee_whiz_2/cli/util.py
gee_whiz_2/config/__init__.py
gee_whiz_2/config/common.py
gee_whiz_2/config/config_0_1_0.py
gee_whiz_2/exceptions/__init__.py
gee_whiz_2/game/__init__.py
gee_whiz_2/game/game.py
gee_whiz_2/profiles/__init__.py
gee_whiz_2/profiles/profiles.py
gee_whiz_2/util/__init__.py
gee_whiz_2/util/downloader.py
gee_whiz_2/util/logger.py
gee_whiz_2/util/picker.py
gee_whiz_2/util/status.py
gee_whiz_2/util/tui.py
gee_whiz_2-2.0.0b4.dist-info/entry_points.txt
gee_whiz_2-2.0.0b4.dist-info/LICENSE
gee_whiz_2-2.0.0b4.dist-info/WHEEL
gee_whiz_2-2.0.0b4.dist-info/METADATA
gee_whiz_2-2.0.0b4.dist-info/RECORD
